LICENSE.txt
MANIFEST.in
README.md
README.rst
blog-post.md
blog-post.rst
setup.cfg
setup.py
picaxe/__init__.py
picaxe/__version__.py
picaxe/cl_utils.py
picaxe/default_settings.yaml
picaxe/picaxe.py
picaxe/utKit.py
picaxe.egg-info/PKG-INFO
picaxe.egg-info/SOURCES.txt
picaxe.egg-info/dependency_links.txt
picaxe.egg-info/entry_points.txt
picaxe.egg-info/not-zip-safe
picaxe.egg-info/requires.txt
picaxe.egg-info/top_level.txt
picaxe/commonutils/__init__.py
picaxe/commonutils/getpackagepath.py
picaxe/tests/__init__.py
picaxe/tests/test_picaxe.py
picaxe/tests/input/example_settings.yaml
picaxe/tests/input/thespacedoctor_icon_dark_circle.png
picaxe/tests/output/example_settings.yaml
picaxe/tests/output/thespacedoctor_icon_dark_circle.png