Metadata-Version: 1.1
Name: picaxe
Version: 0.2.0
Summary: A python package and command-line tools to work with the Flickr API to upload images, sort images, generate MD image reference links etc
Home-page: https://github.com/thespacedoctor/picaxe
Author: David Young
Author-email: davidrobertyoung@gmail.com
License: MIT
Download-URL: https://github.com/thespacedoctor/picaxe/archive/v0.2.0.zip
Keywords: flickr, images
Platform: UNKNOWN
Classifier: Development Status :: 4 - Beta
Classifier: License :: OSI Approved :: MIT License
Classifier: Programming Language :: Python :: 2.7
Classifier: Topic :: Utilities
